specklia/__init__.py
specklia/chunked_transfer.py
specklia/client.py
specklia/internal_admin_client.py
specklia/utilities.py
specklia-1.9.111.dist-info/LICENCE
specklia-1.9.111.dist-info/METADATA
specklia-1.9.111.dist-info/WHEEL
specklia-1.9.111.dist-info/top_level.txt
specklia-1.9.111.dist-info/RECORD
