Metadata-Version: 2.2
Name: specklia
Version: 1.9.111
Summary: Python client for Specklia, a geospatial point cloud database by Earthwave.
Home-page: https://specklia.earthwave.co.uk/
Author: Earthwave Ltd
Author-email: support@earthwave.co.uk
License: MIT
Project-URL: Homepage, https://specklia.earthwave.co.uk/
Project-URL: Changelog, https://specklia.earthwave.co.uk/generated_docs/change_log.html
Project-URL: Documentation, https://specklia.earthwave.co.uk/generated_docs/index.html
Project-URL: Twitter, https://twitter.com/earth__wave
Classifier: Development Status :: 4 - Beta
Classifier: Programming Language :: Python :: 3.11
Classifier: Topic :: Database :: Front-Ends
Classifier: Topic :: Scientific/Engineering :: GIS
Classifier: Topic :: Software Development :: Libraries :: Python Modules
Classifier: License :: OSI Approved :: MIT License
Classifier: Operating System :: OS Independent
Classifier: Environment :: Console
Classifier: Intended Audience :: Science/Research
Requires-Python: >=3.11
License-File: LICENCE
Requires-Dist: blosc
Requires-Dist: geopandas
Requires-Dist: pandas
Requires-Dist: pyarrow
Requires-Dist: rasterio
Requires-Dist: requests
Requires-Dist: shapely
Dynamic: author
Dynamic: author-email
Dynamic: classifier
Dynamic: description
Dynamic: description-content-type
Dynamic: home-page
Dynamic: license
Dynamic: project-url
Dynamic: requires-dist
Dynamic: requires-python
Dynamic: summary
